xh_dual_layer_app_engine/CommandTemplate.py
xh_dual_layer_app_engine/ExtractFromFile.py
xh_dual_layer_app_engine/Layer1AppEngine.py
xh_dual_layer_app_engine/__init__.py
xh_dual_layer_app_engine-0.0.4.dist-info/LICENSE.txt
xh_dual_layer_app_engine-0.0.4.dist-info/METADATA
xh_dual_layer_app_engine-0.0.4.dist-info/WHEEL
xh_dual_layer_app_engine-0.0.4.dist-info/top_level.txt
xh_dual_layer_app_engine-0.0.4.dist-info/RECORD
