Metadata-Version: 2.1
Name: xh-dual-layer-app-engine
Version: 0.0.4
Summary: A library re-orangize the builtin argparser api to simply bootstrap app with second layer command
Author-email: xethhung <pypi@xethh.dev>
Project-URL: Homepage, https://github.com/xh-dev/xh-dual-layer-app-engine
Project-URL: Bug Tracker, https://github.com/xh-dev/xh-dual-layer-app-engine
Classifier: Programming Language :: Python :: 3
Classifier: License :: OSI Approved :: MIT License
Classifier: Operating System :: OS Independent
Requires-Python: >=3.6
License-File: LICENSE.txt
